prefect_slurm_worker/__init__.py
prefect_slurm_worker/apptainer.py
prefect_slurm_worker/worker.py
prefect_slurm_worker/experimental/__init__.py
prefect_slurm_worker/experimental/decorators.py
prefect_slurm_worker-0.11.0.dist-info/METADATA
prefect_slurm_worker-0.11.0.dist-info/WHEEL
prefect_slurm_worker-0.11.0.dist-info/entry_points.txt
prefect_slurm_worker-0.11.0.dist-info/RECORD
