Metadata-Version: 2.4
Name: prefect-slurm-worker
Version: 0.11.0
Summary: Default template for PDM package
Author-email: svenrdz <svenbmr@gmail.com>
License: MIT
Requires-Python: >=3.10
Requires-Dist: prefect[docker]>=3.3
